common/__init__.py
common/utils.py
crew-common/__init__.py
crew-common/utils.py
crewCommon/__init__.py
crewCommon/utils.py
crew_common-0.0.0.5.dist-info/METADATA
crew_common-0.0.0.5.dist-info/WHEEL
crew_common-0.0.0.5.dist-info/top_level.txt
crew_common-0.0.0.5.dist-info/RECORD
