Metadata-Version: 2.1
Name: crew-common
Version: 0.0.0.5
Summary: CrewSquare Common
Home-page: https://www.crewsquare.co.kr/
Author: crewsquare
Author-email: kyle@crewsquare.co.kr
License: MIT
Platform: UNKNOWN
Requires-Python: >=3
